camshell/__init__.py
camshell/camshell_core.py
camshell/cli/cli.py
camshell/display/__init__.py
camshell/display/displays.py
camshell/interfaces.py
camshell/vision/__gi.py
camshell/vision/__init__.py
camshell/vision/camera.py
camshell/vision/gstream_components.py
camshell/vision/gstream_pipeline.py
camshell-0.1.8.dist-info/LICENSE
camshell-0.1.8.dist-info/METADATA
camshell-0.1.8.dist-info/WHEEL
camshell-0.1.8.dist-info/entry_points.txt
camshell-0.1.8.dist-info/RECORD
