Metadata-Version: 2.1
Name: camshell
Version: 0.1.8
Summary: A simple tool to stream camera in shell.
License: MIT
Author: Aref Mehr
Author-email: aref.moqadam@gmail.com
Requires-Python: >=3.10,<4.0
Classifier: License :: OSI Approved :: MIT License
Classifier: Programming Language :: Python :: 3
Classifier: Programming Language :: Python :: 3.10
Classifier: Programming Language :: Python :: 3.11
Classifier: Programming Language :: Python :: 3.12
Classifier: Programming Language :: Python :: 3.13
Requires-Dist: click (>=8.1.7,<9.0.0)
Requires-Dist: loguru (>=0.7.3,<0.8.0)
Requires-Dist: pygobject (>=3.48.0)
Requires-Dist: rich (>=13.9.4,<14.0.0)
